LICENSE
README.md
setup.cfg
setup.py
reddit_sentiment/__init__.py
reddit_sentiment/cli.py
reddit_sentiment/sentiment.py
reddit_sentiment.egg-info/PKG-INFO
reddit_sentiment.egg-info/SOURCES.txt
reddit_sentiment.egg-info/dependency_links.txt
reddit_sentiment.egg-info/entry_points.txt
reddit_sentiment.egg-info/namespace_packages.txt
reddit_sentiment.egg-info/requires.txt
reddit_sentiment.egg-info/top_level.txt
reddit_sentiment/api/__init__.py
reddit_sentiment/api/api.py
reddit_sentiment/api/reddit.py
reddit_sentiment/api/scraper.py
tests/__init__.py
tests/test_scraper.py
tests/test_sentiment.py