Metadata-Version: 2.1
Name: reddit-sentiment
Version: 1.0
Summary: Reddit Sentiment Analyzer
Home-page: https://github.com/fishtoadsoft/reddit-sentiment-analyzer
Download-URL: https://github.com/fishtoadsoft/reddit-sentiment-analyzer/archive/refs/tags/v1.0.0.tar.gz
Author: Fernando Diaz
Author-email: awkwardferny@gmail.com
License: MIT
Keywords: reddit,sentiment,analysis,nlp
Platform: Any
Classifier: Development Status :: 4 - Beta
Classifier: Intended Audience :: Science/Research
Classifier: License :: OSI Approved :: MIT License
Classifier: Topic :: Software Development :: Build Tools
Classifier: Programming Language :: Python :: 3
Classifier: Programming Language :: Python :: 3.10
Classifier: Environment :: Console
License-File: LICENSE
